lgr/__init__.py
lgr/admin.py
lgr/apps.py
lgr/drf.py
lgr/filters.py
lgr/forms.py
lgr/helpers.py
lgr/manage.py
lgr/mixin.py
lgr/models.py
lgr/settings.py
lgr/signals.py
lgr/tests.py
lgr/urls.py
lgr/validators.py
lgr/views.py
lgr/wsgi.py
lgr/static/index.html
lgr/static/css/buefy.min.css
lgr/static/css/materialdesignicons.min.css
lgr/static/js/axios.min.js
lgr/static/js/buefy.min.js
lgr/static/js/vue.js
lgr/templates/loaned.html
lgr/templates/admin/custom_change_form.html
lgr/templates/admin/custom_change_list.html
lgr-0.1.3.dist-info/LICENSE
lgr-0.1.3.dist-info/METADATA
lgr-0.1.3.dist-info/WHEEL
lgr-0.1.3.dist-info/entry_points.txt
lgr-0.1.3.dist-info/top_level.txt
lgr-0.1.3.dist-info/RECORD
