Metadata-Version: 2.1
Name: lgr
Version: 0.1.3
Summary: UNKNOWN
Home-page: UNKNOWN
Author: UNKNOWN
Author-email: UNKNOWN
License: UNKNOWN
Platform: UNKNOWN
Requires-Dist: django
Requires-Dist: django-auth-ldap
Requires-Dist: djangorestframework
Requires-Dist: django-filter
Requires-Dist: mysqlclient
Requires-Dist: django-nose
Requires-Dist: coverage
